setup.py
retweet/__init__.py
retweet/cliparse.py
retweet/confparse.py
retweet/main.py
retweet/senttweets.py
retweet/tweetwasposted.py
retweet/validate.py
retweet/waitamoment.py
retweet.egg-info/PKG-INFO
retweet.egg-info/SOURCES.txt
retweet.egg-info/dependency_links.txt
retweet.egg-info/requires.txt
retweet.egg-info/top_level.txt
scripts/retweet