Metadata-Version: 1.1
Name: retweet
Version: 0.8
Summary: twitter bot to retweet all tweets from a user
Home-page: https://github.com/chaica/retweet
Author: Carl Chenet
Author-email: chaica@ohmytux.com
License: GNU GPL v3
Download-URL: https://github.com/chaica/retweet
Platform: UNKNOWN
Classifier: Intended Audience :: End Users/Desktop
Classifier: Environment :: Console
Classifier: License :: OSI Approved :: GNU General Public License (GPL)
Classifier: Operating System :: POSIX :: Linux
Classifier: Programming Language :: Python :: 3.4
